diffilqrax/VERSION
diffilqrax/__init__.py
diffilqrax/diff_ilqr.py
diffilqrax/diff_lqr.py
diffilqrax/exact.py
diffilqrax/ilqr.py
diffilqrax/lqr.py
diffilqrax/parallel_dilqr.py
diffilqrax/parallel_dlqr.py
diffilqrax/parallel_ilqr.py
diffilqrax/plqr.py
diffilqrax/typs.py
diffilqrax/utils.py
diffilqrax-0.0.7.dist-info/LICENSE
diffilqrax-0.0.7.dist-info/METADATA
diffilqrax-0.0.7.dist-info/WHEEL
diffilqrax-0.0.7.dist-info/top_level.txt
diffilqrax-0.0.7.dist-info/RECORD
