Metadata-Version: 2.2
Name: diffilqrax
Version: 0.0.7
Summary: Differentiable iLQR algorithm for dynamical systems
Author-email: Thomas Soares Mullen <thomasmullen96@gmail.com>, Marine Schimel <marine.schimel@hotmail.fr>
License:                                  Apache License
Project-URL: Homepage, https://github.com/ThomasMullen/diffilqrax
Project-URL: Bug Tracker, https://github.com/ThomasMullen/diffilqrax/issues
Keywords: lqr,ilqr,optimal control,Optimal Control,kalman
Classifier: Development Status :: 3 - Alpha
Classifier: Intended Audience :: Science/Research
Classifier: Intended Audience :: Education
Classifier: Topic :: Scientific/Engineering
Classifier: Topic :: Scientific/Engineering :: Artificial Intelligence
Classifier: Topic :: Scientific/Engineering :: Physics
Classifier: License :: OSI Approved :: Apache Software License
Classifier: Programming Language :: Python :: 3
Classifier: Programming Language :: Python :: 3.10
Classifier: Programming Language :: Python :: 3.11
Classifier: Programming Language :: Python :: 3.12
Classifier: Programming Language :: Python :: 3 :: Only
Requires-Python: >=3.10
License-File: LICENSE
Requires-Dist: tdqm
Requires-Dist: numpy
Requires-Dist: jax
Requires-Dist: jaxopt
Requires-Dist: optax
Requires-Dist: chex
Requires-Dist: pytest
Requires-Dist: matplotlib
Requires-Dist: build
Provides-Extra: dev
Requires-Dist: matplotlib; extra == "dev"
Requires-Dist: jax; extra == "dev"
Requires-Dist: jaxopt; extra == "dev"
Requires-Dist: chex; extra == "dev"
Requires-Dist: numpy; extra == "dev"
Requires-Dist: scipy; extra == "dev"
Requires-Dist: tqdm; extra == "dev"
Requires-Dist: jax_dataclasses; extra == "dev"
Requires-Dist: chex; extra == "dev"
Requires-Dist: pytest; extra == "dev"
Requires-Dist: black; extra == "dev"
Requires-Dist: build; extra == "dev"
Requires-Dist: twine; extra == "dev"
Requires-Dist: pylint; extra == "dev"
Provides-Extra: doc
Requires-Dist: matplotlib; extra == "doc"
Requires-Dist: jax; extra == "doc"
Requires-Dist: jaxopt; extra == "doc"
Requires-Dist: chex; extra == "doc"
Requires-Dist: numpy; extra == "doc"
Requires-Dist: scipy; extra == "doc"
Requires-Dist: tqdm; extra == "doc"
Requires-Dist: jax_dataclasses; extra == "doc"
Requires-Dist: chex; extra == "doc"
Requires-Dist: pytest; extra == "doc"
Requires-Dist: black; extra == "doc"
Requires-Dist: build; extra == "doc"
Requires-Dist: twine; extra == "doc"
Requires-Dist: pylint; extra == "doc"
